opdesign/__init__.py
opdesign/design.py
opdesign-0.0.3.dist-info/LICENSE
opdesign-0.0.3.dist-info/METADATA
opdesign-0.0.3.dist-info/WHEEL
opdesign-0.0.3.dist-info/top_level.txt
opdesign-0.0.3.dist-info/RECORD
